Metadata-Version: 2.4
Name: myconfig-osx
Version: 1.3.2
Summary: macOS configuration backup and restore tool
Author-email: Kyle <kehr.china@gmail.com>
Maintainer-email: Kyle <kehr.china@gmail.com>
License-Expression: GPL-2.0
Project-URL: Homepage, https://github.com/kehr/myconfig
Project-URL: Documentation, https://github.com/kehr/myconfig/blob/main/docs/
Project-URL: Repository, https://github.com/kehr/myconfig
Project-URL: Bug Tracker, https://github.com/kehr/myconfig/issues
Project-URL: Changelog, https://github.com/kehr/myconfig/blob/main/docs/OPTIMIZATION_SUMMARY.md
Keywords: macos,backup,restore,configuration,dotfiles,homebrew
Classifier: Development Status :: 5 - Production/Stable
Classifier: Environment :: Console
Classifier: Environment :: MacOS X
Classifier: Intended Audience :: Developers
Classifier: Intended Audience :: System Administrators
Classifier: Operating System :: MacOS
Classifier: Programming Language :: Python :: 3
Classifier: Programming Language :: Python :: 3.8
Classifier: Programming Language :: Python :: 3.9
Classifier: Programming Language :: Python :: 3.10
Classifier: Programming Language :: Python :: 3.11
Classifier: Programming Language :: Python :: 3.12
Classifier: Topic :: System :: Archiving :: Backup
Classifier: Topic :: System :: Installation/Setup
Classifier: Topic :: System :: Systems Administration
Classifier: Topic :: Utilities
Requires-Python: >=3.8
License-File: LICENSE
Requires-Dist: tomli>=1.2.0
Requires-Dist: click>=8.0.0
Requires-Dist: rich>=13.0.0
Requires-Dist: pathlib2>=2.3.0; python_version < "3.4"
Provides-Extra: dev
Requires-Dist: pytest>=7.0; extra == "dev"
Requires-Dist: pytest-cov>=4.0; extra == "dev"
Requires-Dist: pytest-mock>=3.10; extra == "dev"
Requires-Dist: black>=22.0; extra == "dev"
Requires-Dist: flake8>=4.0; extra == "dev"
Requires-Dist: mypy>=1.0; extra == "dev"
Requires-Dist: pre-commit>=3.0; extra == "dev"
Requires-Dist: tox>=4.0; extra == "dev"
Provides-Extra: build
Requires-Dist: build>=1.0.0; extra == "build"
Requires-Dist: twine>=4.0.0; extra == "build"
Requires-Dist: wheel>=0.40.0; extra == "build"
Provides-Extra: encryption
Requires-Dist: cryptography>=3.4; extra == "encryption"
Provides-Extra: docs
Requires-Dist: sphinx>=6.0.0; extra == "docs"
Requires-Dist: sphinx-rtd-theme>=1.0.0; extra == "docs"
Requires-Dist: myst-parser>=1.0.0; extra == "docs"
Dynamic: license-file
